doonook_chinese_calendar/__init__.py
doonook_chinese_calendar/api/__init__.py
doonook_chinese_calendar/api/astro_endpoints.py
doonook_chinese_calendar/api/endpoints.py
doonook_chinese_calendar/cli.py
doonook_chinese_calendar/core/__init__.py
doonook_chinese_calendar/core/config.py
doonook_chinese_calendar/core/database.py
doonook_chinese_calendar/migrations/README
doonook_chinese_calendar/migrations/env.py
doonook_chinese_calendar/migrations/script.py.mako
doonook_chinese_calendar/migrations/versions/75c3add9cb65_initial_migration.py
doonook_chinese_calendar/models/__init__.py
doonook_chinese_calendar/models/astro.py
doonook_chinese_calendar/models/calendar.py
doonook_chinese_calendar/schemas/__init__.py
doonook_chinese_calendar/schemas/astro.py
doonook_chinese_calendar/schemas/calendar.py
doonook_chinese_calendar/services/__init__.py
doonook_chinese_calendar/services/astro_service.py
doonook_chinese_calendar/services/calendar_service.py
doonook_chinese_calendar/utils/__init__.py
doonook_chinese_calendar/utils/lunar_solar_converter.py
doonook_chinese_calendar-0.1.3.dist-info/METADATA
doonook_chinese_calendar-0.1.3.dist-info/WHEEL
doonook_chinese_calendar-0.1.3.dist-info/entry_points.txt
doonook_chinese_calendar-0.1.3.dist-info/RECORD
